seeder/__init__.py
seeder/basic_seeder.py
seeder/exceptions.py
seeder/resolving_seeder.py
seeder/resources/resolver.schema.json
sqlalchemy_seeder-0.3.0.dist-info/DESCRIPTION.rst
sqlalchemy_seeder-0.3.0.dist-info/METADATA
sqlalchemy_seeder-0.3.0.dist-info/RECORD
sqlalchemy_seeder-0.3.0.dist-info/WHEEL
sqlalchemy_seeder-0.3.0.dist-info/metadata.json
sqlalchemy_seeder-0.3.0.dist-info/top_level.txt
sqlalchemyseeder/__init__.py
sqlalchemyseeder/basic_seeder.py
sqlalchemyseeder/exceptions.py
sqlalchemyseeder/resolving_seeder.py
sqlalchemyseeder/resources/resolver.schema.json
