Metadata-Version: 1.2
Name: sqlalchemy-seeder
Version: 0.3.0
Summary: Tool for creating (and persisting) SQLAlchemy entities from a simple data format.
Home-page: https://github.com/RiceKab/sqlalchemy-seeder
Author: Kevin CY Tang
Author-email: kevin@cyborn.be
License: MIT
Keywords: sqlalchemy json yaml seed
Platform: UNKNOWN
Classifier: Development Status :: 3 - Alpha
Classifier: Intended Audience :: Developers
Classifier: Topic :: Utilities
Classifier: License :: OSI Approved :: MIT License
Classifier: Programming Language :: Python :: 2.7
Classifier: Programming Language :: Python :: 3
Requires-Python: >=2.7
